{
	
	"diplomaticRelation_None": {
		"english": "-",
		"german": "-",
		"french": "-",
		"dutch": "-",
		"portuguese": "-",
		"russian": "-",
	},
	"diplomaticRelation_GotPresents": {
		"english": "Got Presents",
		"german": "Geschenke erhalten",
		"french": "A des cadeaux", 
		"dutch": "Geschenken gehad",
		"portuguese": "Tem presentes",
		"russian": "Получил подарки",
	},
	"diplomaticRelation_Kindhearted": {
		"english": "Kindhearted",
		"german": "Gutherzig",
		"french": "Bienveillant", 
		"dutch": "Goedhartig",
		"portuguese": "Bondoso",
		"russian": "Доброжелательный",
	},
	"diplomaticRelation_Xenophobic": {
		"english": "Xenophobic",
		"german": "Fremdenfeindlich",
		"french": "Xénophobe", 
		"dutch": "Xenofobe",
		"portuguese": "Xenófobo",
		"russian": "Ксенофоб",
	},
	"diplomaticRelation_KilledOneOfOurPeople": {
		"english": "One of our people was killed",
		"german": "Einer der unserern wurde umgebracht",
		"french": "L'un des nôtres a été tué",
		"dutch": "Iemand van ons is vermoord",
		"portuguese": "Um dos nossos foi assassinado",
		"russian": "Один из наших был убит",
	},
	"diplomaticRelation_GoodTrade": {
		"english": "Good Trade",
		"german": "Guter Handel",
		"french": "Bons échanges commerciaux", 
		"dutch": "Goede Handel",
		"portuguese": "Bom comércio",
		"russian": "Хорошая сделка",
	},
	"diplomaticRelation_EnviousOfWealthyColony": {
		"english": "Envious of Wealthy Colony",
		"german": "Neidisch auf reiche Kolonie",
		"french": "Envieux d'une riche colonie",
		"dutch": "Jaloers op Rijke Kolonie",
		"portuguese": "Inveja da colônia rica",
		"russian": "Завидует богатой колонии",
	},
	"diplomaticRelation_WorriedAboutLargeColony": {
		"english": "WorriedAboutLargeColony",
		"german": "Beunruhigt durch große Kolonie",
		"french": "Inquiet au sujet d'une grande colonie",
		"dutch": "Bezorgt over Grote Kolonie",
		"portuguese": "Preocupado com a grande colônia",
		"russian": "Обеспокоен большой колонией",
		
	},
	"diplomaticRelation_LastingFriendship": {
		"english": "Lasting Friendship",
		"german": "Lange währende Freundschaft",
		"french": "Amitié durable", 
		"dutch": "Langdurende Vriendschap",
		"portuguese": "Amizade duradoura",
		"russian": "Прочная дружба",
	},
	"diplomaticRelation_LongTimeNemisis": {
		"english": "Long Time Nemisis",
		"german": "Andauernde Feindschaft",
		"french": "Ennemi juré de longue date",
		"dutch": "Langdurende Vijandschap",
		"portuguese": "Nêmesis de longo tempo",
		"russian": "Долгое время без воин",
	},
	"diplomaticRelation_GotAttackedWithNoReason": {
		"english": "Got Attacked with no Reason",
		"german": "Wurde grundlos angegriffen",
		"french": "A été attaqué sans raison",
		"dutch": "Is zonder reden aangevallen",
		"portuguese": "Foi atacado sem motivo",
		"russian": "Атакованы без причины",
	},
	"diplomaticRelation_Fought": {
		"english": "Fought",
		"german": "Kämpfe",
		"french": "Disputes",
		"dutch": "Gevochten",
		"portuguese": "Lutou",
		"russian": "Сражались",
	},
	"diplomaticRelation_DemandedTributeFromUs": {
		"english": "You demanded a tribute",
		"german": "Ihr habt einen Tribut gefordert",
		"french": "Vous avez exigé un hommage",
		"dutch": "Jij hebt een eerbetoon geëist",
		"portuguese": "Você exigiu um tributo",
		"russian": "Вы потребовали дань",
	},
	"diplomaticRelation_OurTributePaid": {
		"english": "Our Tribute was Paid",
		"german": "Unser Tribut wurde bezahlt",
		"french": "Notre hommage a été rendu",
		"dutch": "Ons Eerbetoon is Betaalt",
		"portuguese": "Nosso tributo foi pago",
		"russian": "Дань была оплачена-",
	},
	"diplomaticRelation_OurTributeNotPaid": {
		"english": "Our Tribute was not Paid",
		"german": "Unser Tribut wurde nicht bezahlt",
		"french": "Notre hommage n'a pas été rendu",
		"dutch": "Ons Eerbetoon is niet Betaalt",
		"portuguese": "Nosso tributo não foi pago",
		"russian": "Дань не была оплачена",
	},
	"diplomaticRelation_TendedToInjured": {
		"english": "Our injured were tended to",
		"german": "Unsere Verletzten wurden umsorgt",
		"french": "Nos blessés ont été tentés à",
		"dutch": "Onze gewonden zijn verzorgt",
		"portuguese": "Nossos feridos foram tendidos a",
		"russian": "Наши раненные позаботились о",
	},
	"diplomaticRelation_StatuePresent": {
		"english": "We got a statue as a present",
		"german": "Wir haben eine Statue als Geschenk bekommen",
		"french": "Nous avons reçu une statue en guise de cadeau",
		"dutch": "We hebben een standbeeld cadeau gekregen",
		"portuguese": "Nós temos uma estátua como presente",
		"russian": "Мы получили статую в подарок",
	},
	"diplomaticRelation_EagerToTrade": {
		"english": "Eager to Trade",
		"german": "Freut sich auf Handel",
		"french": "Désireux de faire des affaires",
		"dutch": "Wil graag handelen",
		"portuguese": "Ansioso para o comércio",
		"russian": "Готов торговать",
	},
	"diplomaticRelation_HadToMakeDetourToVisit": {
		"english": "Had to take a Detour to Visit",
		"german": "Musste Umweg nehmen für Besuch",
		"french": "A dû faire un détour pour visiter",
		"dutch": "Moest een omweg nemen voor bezoek",
		"portuguese": "Teve que fazer um desvio para visitar",
		"russian": "Пришлось сделат круг для посещения",
	},
}
