{
	// Tier I
	"tech_woodworking": {
		"english": "Woodworking",
		"german": "Holzverarbeitung"
	},
	"tech_farming": {
		"english": "Farming",
		"german": "Landwirtschaft"
	},

	// Tier II
	"tech_architectureI": {
		"english": "Architecture I",
		"german": "Architektur I"
	},
	"tech_masonry": {
		"english": "Masonry",
		"german": "Steinmetzerei"
	},
	"tech_furnitureI": {
		"english": "Furniture I",
		"german": "Möbel I"
	},
	"tech_gardening": {
		"english": "Gardening",
		"german": "Gärtnern"
	},
	"tech_writing": {
		"english": "Writing",
		"german": "Schrift"
	},

	// Tier III
	"tech_rangedWeapons": {
		"english": "Ranged Weapons",
		"german": "Fernkampfwaffen"
	},
	"tech_architectureII": {
		"english": "Architecture II",
		"german": "Architektur II"
	},
	"tech_furnitureII": {
		"english": "Furniture II",
		"german": "Möbel II"
	},
	"tech_decoration": {
		"english": "Decoration",
		"german": "Dekoration"
	},
	"tech_irrigation": {
		"english": "Irrigation",
		"german": "Bewässerung"
	},
	"tech_medicine": {
		"english": "Basic Medicine",
		"german": "Einfache Medizin"
	},

	// Tier IV
	"tech_towers": {
		"english": "Towers",
		"german": "Turmbau"
	},
	"tech_furnitureIII": {
		"english": "Furniture III",
		"german": "Möbel III"
	},
	"tech_tailoring": {
		"english": "Tailoring",
		"german": "Schneiderei"
	},
	"tech_advancedCooking": {
		"english": "Advanced Cooking",
		"german": "Fortgeschrittenes Kochen"
	},
	"tech_alchemy": {
		"english": "Alchemy",
		"german": "Alchemie"
	},

	// Tier V
	"tech_strongWatchtowers": {
		"english": "Strong Watchtowers",
		"german": "Starke Wachtürme"
	},
	"tech_forging": {
		"english": "Forging",
		"german": "Schmieden"
	},
	"tech_grainProcessing": {
		"english": "Grain Processing",
		"german": "Getreideverarbeitung"
	},
}